imbi_automations/__init__.py
imbi_automations/claude.py
imbi_automations/cli.py
imbi_automations/committer.py
imbi_automations/condition_checker.py
imbi_automations/controller.py
imbi_automations/errors.py
imbi_automations/git.py
imbi_automations/imc.py
imbi_automations/mixins.py
imbi_automations/per_project_logging.py
imbi_automations/prompts.py
imbi_automations/py.typed
imbi_automations/tracker.py
imbi_automations/utils.py
imbi_automations/workflow_engine.py
imbi_automations/workflow_filter.py
imbi_automations/actions/__init__.py
imbi_automations/actions/callablea.py
imbi_automations/actions/claude.py
imbi_automations/actions/docker.py
imbi_automations/actions/filea.py
imbi_automations/actions/git.py
imbi_automations/actions/github.py
imbi_automations/actions/imbi.py
imbi_automations/actions/shell.py
imbi_automations/actions/template.py
imbi_automations/actions/prompts/last-error.md.j2
imbi_automations/actions/prompts/planning-with-errors.md.j2
imbi_automations/actions/prompts/with-plan.md.j2
imbi_automations/claude-code/CLAUDE.md
imbi_automations/claude-code/agents/planning.md.j2
imbi_automations/claude-code/agents/task.md.j2
imbi_automations/claude-code/agents/validation.md.j2
imbi_automations/clients/__init__.py
imbi_automations/clients/github.py
imbi_automations/clients/http.py
imbi_automations/clients/imbi.py
imbi_automations/models/__init__.py
imbi_automations/models/base.py
imbi_automations/models/claude.py
imbi_automations/models/configuration.py
imbi_automations/models/git.py
imbi_automations/models/github.py
imbi_automations/models/imbi.py
imbi_automations/models/mcp.py
imbi_automations/models/resume_state.py
imbi_automations/models/sonarqube.py
imbi_automations/models/validators.py
imbi_automations/models/workflow.py
imbi_automations/prompts/commit.md.j2
imbi_automations/prompts/pull-request-summary.md.j2
imbi_automations-1.0.0b5.dist-info/METADATA
imbi_automations-1.0.0b5.dist-info/WHEEL
imbi_automations-1.0.0b5.dist-info/entry_points.txt
imbi_automations-1.0.0b5.dist-info/licenses/LICENSE
imbi_automations-1.0.0b5.dist-info/RECORD
