Metadata-Version: 2.4
Name: imbi-automations
Version: 1.0.0b5
Summary: CLI tool for executing automated workflows across Imbi projects with AI-powered transformations and GitHub PR integration.
Project-URL: Homepage, https://AWeber-Imbi.github.io/imbi-automations/
Project-URL: Repository, https://github.com/AWeber-Imbi/imbi-automations
Project-URL: Bug Tracker, https://github.com/AWeber-Imbi/imbi-automations/issues
Author-email: "Gavin M. Roy" <gavinr@aweber.com>
License: BSD-3-Clause
License-File: LICENSE
Keywords: claude,cli,github,imbi,llm
Classifier: Development Status :: 3 - Alpha
Classifier: Environment :: Console
Classifier: Intended Audience :: System Administrators
Classifier: License :: OSI Approved :: BSD License
Classifier: Natural Language :: English
Classifier: Operating System :: OS Independent
Classifier: Programming Language :: Python :: 3
Classifier: Programming Language :: Python :: 3.12
Classifier: Programming Language :: Python :: 3.13
Classifier: Programming Language :: Python :: 3.14
Classifier: Topic :: Database
Classifier: Topic :: System :: Systems Administration
Classifier: Typing :: Typed
Requires-Python: >=3.12
Requires-Dist: anthropic[bedrock]
Requires-Dist: async-lru
Requires-Dist: claude-agent-sdk>=0.1.13
Requires-Dist: colorlog
Requires-Dist: httpx
Requires-Dist: jinja2
Requires-Dist: msgpack>=1.0.0
Requires-Dist: pydantic
Requires-Dist: pydantic-settings
Requires-Dist: pytimeparse2>=1.7.1
Requires-Dist: rich
Requires-Dist: semver
Requires-Dist: truststore
Requires-Dist: yarl
